tokysnatcher/__main__.py
tokysnatcher/chapters.py
tokysnatcher/download.py
tokysnatcher/search.py
tokysnatcher-0.3.2.dist-info/licenses/LICENSE
tokysnatcher-0.3.2.dist-info/METADATA
tokysnatcher-0.3.2.dist-info/WHEEL
tokysnatcher-0.3.2.dist-info/entry_points.txt
tokysnatcher-0.3.2.dist-info/top_level.txt
tokysnatcher-0.3.2.dist-info/RECORD
